README.md
setup.py
src/vdk/plugin/properties_fs/fs_properties_client.py
src/vdk/plugin/properties_fs/fs_properties_plugin.py
src/vdk_properties_fs.egg-info/PKG-INFO
src/vdk_properties_fs.egg-info/SOURCES.txt
src/vdk_properties_fs.egg-info/dependency_links.txt
src/vdk_properties_fs.egg-info/entry_points.txt
src/vdk_properties_fs.egg-info/requires.txt
src/vdk_properties_fs.egg-info/top_level.txt
tests/test_fs_properties_plugin.py